Metadata-Version: 2.1
Name: yura112312321321213213-ibdfiu9hdfudfuy8gby123
Version: 1.0
Summary: Мій проєкт
Author: Yurii
Author-email: 123@gmail.com
